pyson0/__init__.py
pyson0/json0.py
pyson0/json0diff.py
pyson0-0.1.dist-info/LICENSE
pyson0-0.1.dist-info/METADATA
pyson0-0.1.dist-info/WHEEL
pyson0-0.1.dist-info/top_level.txt
pyson0-0.1.dist-info/RECORD
