Metadata-Version: 2.1
Name: pyson0
Version: 0.1
Summary: This package ports the json0-ot-diff and ottypes/json0 to python.
Home-page: https://github.com/lbragues/pyson0
Author: Leandro Braguês
Author-email: lbragues@gmail.com
License: UNKNOWN
Platform: UNKNOWN
Classifier: Programming Language :: Python :: 3
Classifier: License :: OSI Approved :: MIT License
Classifier: Operating System :: OS Independent
Requires-Python: >=2.7
